{"apiCode":"B7D57DB7","data":[{"ascentDuration":0,"avgCadence":158,"avgHeartRate":163,"avgPace":332,"avgPower":216,"avgSpeed":0,"calorie":773778,"count":0,"countAvgHr":0,"countAvgSpeed":0,"createTimestamp":1687603648,"createTimezone":32,"deviceId":"COROS PACE 2 8735E5","deviceSportMode":0,"distance":8853.13,"duration":2936,"durationMs":"2935.75","endTime":1687601926,"endTimeMs":"1687601926.75","endTimezone":32,"extraType":0,"fitCreateTime":"2023-06-24 18:47:41","fitUrl":"https://oss.coros.com/fit/447260452899012608/453012654548615170.fit","fitnessSwitch":0,"happenDate":20230624,"happenDay":20230624,"happenMonth":202306,"imageUrl":"https://map-oss-cn.coros.com/img/453012654548959232.jpg","imageUrlType":1,"isShowMs":1,"labelId":"453012654548615170","laps":0,"max2s":0,"maxSpeed":0,"mode":8,"modifyTime":1689036789,"name":"广州市 跑步","pitch":0,"rdType":0,"recalculateRecord":false,"recovery":false,"sets":0,"speedType":3,"speedValue":332,"speedValueDecimal":332.0,"sportType":100,"startLa":23.038000106811523,"startLo":113.37799835205078,"startTime":1687598562,"startTimeMs":"1687598562.65","startTimezone":32,"state":1,"step":7544,"subMode":1,"subSport":false,"taskStatus":0,"total":0,"totalAvgHr":0,"totalAvgSpeed":0,"totalDecline":10,"totalDeclineDouble":0.0,"totalElevation":4,"totalElevationDouble":0.0,"unit":2,"unitType":2,"uploadedImageData":0,"userId":447260452899012608,"uuid":"00274adf0c890005221a0064168735e5","weatherLocationKey":"WS0DE3FVQQJF","weatherTime":1687598096},{"ascentDuration":0,"avgCadence":156,"avgHeartRate":125,"avgPace":371,"avgPower":201,"avgSpeed":0,"calorie":26708,"count":0,"countAvgHr":0,"countAvgSpeed":0,"createTimestamp":1687513975,"createTimezone":32,"deviceId":"COROS PACE 2 8735E5","deviceSportMode":0,"distance":314.22,"duration":116,"durationMs":"116.47","endTime":1687513536,"endTimeMs":"1687513536.78","endTimezone":32,"extraType":0,"fitCreateTime":"2023-06-23 17:53:04","fitUrl":"https://oss.coros.com/fit/447260452899012608/452988583135969280.fit","fitnessSwitch":0,"happenDate":20230623,"happenDay":20230623,"happenMonth":202306,"imageUrl":"https://map-oss-cn.coros.com/img/452988583136313344.jpg","imageUrlType":1,"isShowMs":1,"labelId":"452988583135969280","laps":0,"max2s":0,"maxSpeed":0,"mode":8,"modifyTime":1689036789,"name":"广州市 跑步","pitch":0,"rdType":0,"recalculateRecord":false,"recovery":false,"sets":0,"speedType":3,"speedValue":371,"speedValueDecimal":371.0,"sportType":100,"startLa":23.042999267578125,"startLo":113.38500213623047,"startTime":1687513420,"startTimeMs":"1687513420.30","startTimezone":32,"state":1,"step":291,"subMode":1,"subSport":false,"taskStatus":0,"total":0,"totalAvgHr":0,"totalAvgSpeed":0,"totalDecline":2,"totalDeclineDouble":0.0,"totalElevation":3,"totalElevationDouble":0.0,"unit":2,"unitType":2,"uploadedImageData":0,"userId":447260452899012608,"uuid":"00274a5d21ce00002d800064168735e5","weatherLocationKey":"WS0DE3FVQQJF","weatherTime":1687511411},{"ascentDuration":0,"avgCadence":158,"avgHeartRate":160,"avgPace":342,"avgPower":210,"avgSpeed":0,"calorie":578215,"count":0,"countAvgHr":0,"countAvgSpeed":0,"createTimestamp":1687346947,"createTimezone":32,"deviceId":"COROS PACE 2 8735E5","deviceSportMode":0,"distance":6847.72,"duration":2341,"durationMs":"2341.13","endTime":1687342603,"endTimeMs":"1687342603.96","endTimezone":32,"extraType":0,"fitCreateTime":"2023-06-21 19:29:21","fitUrl":"https://oss.coros.com/fit/447260452899012608/452943746896527361.fit","fitnessSwitch":0,"happenDate":20230621,"happenDay":20230621,"happenMonth":202306,"imageUrl":"https://map-oss-cn.coros.com/img/452943746898968576.jpg","imageUrlType":1,"isShowMs":1,"labelId":"452943746896527361","laps":0,"max2s":0,"maxSpeed":0,"mode":8,"modifyTime":1687346947,"name":"广州市 跑步","pitch":0,"rdType":0,"recalculateRecord":false,"recovery":false,"sets":0,"speedType":3,"speedValue":342,"speedValueDecimal":342.0,"sportType":100,"startLa":23.052000045776367,"startLo":113.38700103759766,"startTime":1687340262,"startTimeMs":"1687340262.83","startTimezone":32,"state":1,"step":6089,"subMode":1,"subSport":false,"taskStatus":0,"total":0,"totalAvgHr":0,"totalAvgSpeed":0,"totalDecline":12,"totalDeclineDouble":0.0,"totalElevation":10,"totalElevationDouble":0.0,"unit":2,"unitType":2,"uploadedImageData":0,"userId":447260452899012608,"uuid":"00274954ea2b000392810064168735e5","weatherLocationKey":"WS0DE3FVQQJF","weatherTime":1687339496},{"ascentDuration":0,"avgCadence":150,"avgHeartRate":159,"avgPace":352,"avgPower":203,"avgSpeed":0,"calorie":445667,"count":0,"countAvgHr":0,"countAvgSpeed":0,"createTimestamp":1687258619,"createTimezone":32,"deviceId":"COROS PACE 2 8735E5","deviceSportMode":0,"distance":5027.49,"duration":1771,"durationMs":"1770.73","endTime":1687257181,"endTimeMs":"1687257181.82","endTimezone":32,"extraType":0,"fitCreateTime":"2023-06-20 18:57:10","fitUrl":"https://oss.coros.com/fit/447260452899012608/452920036798005250.fit","fitnessSwitch":0,"happenDate":20230620,"happenDay":20230620,"happenMonth":202306,"imageUrl":"https://map-oss-cn.coros.com/img/452920036800446464.jpg","imageUrlType":1,"isShowMs":1,"labelId":"452920036798005250","laps":0,"max2s":0,"maxSpeed":0,"mode":8,"modifyTime":1687346947,"name":"广州市 其它运动","pitch":0,"rdType":0,"recalculateRecord":false,"recovery":false,"sets":0,"speedType":3,"speedValue":352,"speedValueDecimal":352.0,"sportType":100,"startLa":23.038999557495117,"startLo":113.38700103759766,"startTime":1687255250,"startTimeMs":"1687255250.27","startTimezone":32,"state":1,"step":4147,"subMode":1,"subSport":false,"taskStatus":0,"total":0,"totalAvgHr":0,"totalAvgSpeed":0,"totalDecline":4,"totalDeclineDouble":0.0,"totalElevation":2,"totalElevationDouble":0.0,"unit":2,"unitType":2,"uploadedImageData":0,"userId":447260452899012608,"uuid":"002748d332230002f2830064168735e5","weatherLocationKey":"WS0DE3FVQQJF","weatherTime":1687256410},{"ascentDuration":0,"avgCadence":162,"avgHeartRate":159,"avgPace":275,"avgPower":255,"avgSpeed":0,"calorie":179343,"count":0,"countAvgHr":0,"countAvgSpeed":0,"createTimestamp":1687170794,"createTimezone":32,"deviceId":"COROS PACE 2 8735E5","deviceSportMode":0,"distance":2227.29,"duration":613,"durationMs":"613.05","endTime":1687168250,"endTimeMs":"1687168250.98","endTimezone":32,"extraType":0,"fitCreateTime":"2023-06-19 18:33:31","fitUrl":"https://oss.coros.com/fit/447260452899012608/452896461187743746.fit","fitnessSwitch":0,"happenDate":20230619,"happenDay":20230619,"happenMonth":202306,"imageUrl":"https://map-oss-cn.coros.com/img/452896461188087808.jpg","imageUrlType":1,"isShowMs":1,"labelId":"452896461187743746","laps":0,"max2s":0,"maxSpeed":0,"mode":8,"modifyTime":1687346947,"name":"广州市 其它运动","pitch":0,"rdType":0,"recalculateRecord":false,"recovery":false,"sets":0,"speedType":3,"speedValue":275,"speedValueDecimal":275.0,"sportType":100,"startLa":23.042999267578125,"startLo":113.38500213623047,"startTime":1687167637,"startTimeMs":"1687167637.93","startTimezone":32,"state":1,"step":1639,"subMode":1,"subSport":false,"taskStatus":0,"total":0,"totalAvgHr":0,"totalAvgSpeed":0,"totalDecline":1,"totalDeclineDouble":0.0,"totalElevation":2,"totalElevationDouble":0.0,"unit":2,"unitType":2,"uploadedImageData":0,"userId":447260452899012608,"uuid":"0027484d82910000ef790064168735e5","weatherLocationKey":"WS0DE3FVQQJF","weatherTime":1687166411},{"ascentDuration":0,"avgCadence":158,"avgHeartRate":165,"avgPace":325,"avgPower":218,"avgSpeed":0,"calorie":704269,"count":0,"countAvgHr":0,"countAvgSpeed":0,"createTimestamp":1687083438,"createTimezone":32,"deviceId":"COROS PACE 2 8735E5","deviceSportMode":0,"distance":8380.26,"duration":2723,"durationMs":"2722.72","endTime":1687081815,"endTimeMs":"1687081815.78","endTimezone":32,"extraType":0,"fitCreateTime":"2023-06-18 18:17:28","fitUrl":"https://oss.coros.com/fit/447260452899012608/452873011740049410.fit","fitnessSwitch":0,"happenDate":20230618,"happenDay":20230618,"happenMonth":202306,"imageUrl":"https://map-oss-cn.coros.com/img/452873011740393472.jpg","imageUrlType":1,"isShowMs":1,"labelId":"452873011740049410","laps":0,"max2s":0,"maxSpeed":0,"mode":8,"modifyTime":1687346947,"name":"广州市 其它运动","pitch":0,"rdType":0,"recalculateRecord":false,"recovery":false,"sets":0,"speedType":3,"speedValue":325,"speedValueDecimal":325.0,"sportType":100,"startLa":23.05299949645996,"startLo":113.38600158691406,"startTime":1687078837,"startTimeMs":"1687078837.24","startTimezone":32,"state":1,"step":7043,"subMode":1,"subSport":false,"taskStatus":0,"total":0,"totalAvgHr":0,"totalAvgSpeed":0,"totalDecline":16,"totalDeclineDouble":0.0,"totalElevation":15,"totalElevationDouble":0.0,"unit":2,"unitType":2,"uploadedImageData":0,"userId":447260452899012608,"uuid":"002747c602cc00048b7e0064168735e5","weatherLocationKey":"WS0DE3FVQQJF","weatherTime":1687079549},{"ascentDuration":0,"avgCadence":154,"avgHeartRate":163,"avgPace":369,"avgPower":193,"avgSpeed":0,"calorie":1193093,"count":0,"countAvgHr":0,"countAvgSpeed":0,"createTimestamp":1686910612,"createTimezone":32,"deviceId":"COROS PACE 2 8735E5","deviceSportMode":0,"distance":13449.4,"duration":4961,"durationMs":"4960.72","endTime":1686908547,"endTimeMs":"1686908547.13","endTimezone":32,"extraType":0,"fitCreateTime":"2023-06-16 18:17:04","fitUrl":"https://oss.coros.com/fit/447260452899012608/452826619111833601.fit","fitnessSwitch":0,"happenDate":20230616,"happenDay":20230616,"happenMonth":202306,"imageUrl":"https://map-oss-cn.coros.com/img/452826619112177664.jpg","imageUrlType":1,"isShowMs":1,"labelId":"452826619111833601","laps":0,"max2s":0,"maxSpeed":0,"mode":8,"modifyTime":1687346947,"name":"广州市 跑步","pitch":0,"rdType":0,"recalculateRecord":false,"recovery":false,"sets":0,"speedType":3,"speedValue":369,"speedValueDecimal":369.0,"sportType":100,"startLa":23.038000106811523,"startLo":113.37799835205078,"startTime":1686903014,"startTimeMs":"1686903014.23","startTimezone":32,"state":1,"step":12367,"subMode":1,"subSport":false,"taskStatus":0,"total":0,"totalAvgHr":0,"totalAvgSpeed":0,"totalDecline":28,"totalDeclineDouble":0.0,"totalElevation":23,"totalElevationDouble":0.0,"unit":2,"unitType":2,"uploadedImageData":0,"userId":447260452899012608,"uuid":"002746b9b9ef0008714a0064168735e5","weatherLocationKey":"WS0DE3FVQQJF","weatherTime":1686903611},{"ascentDuration":0,"avgCadence":157,"avgHeartRate":163,"avgPace":344,"avgPower":207,"avgSpeed":0,"calorie":738730,"count":0,"countAvgHr":0,"countAvgSpeed":0,"createTimestamp":1686738991,"createTimezone":32,"deviceId":"COROS PACE 2 8735E5","deviceSportMode":0,"distance":8516.05,"duration":2931,"durationMs":"2930.57","endTime":1686737606,"endTimeMs":"1686737606.20","endTimezone":32,"extraType":0,"fitCreateTime":"2023-06-14 18:36:41","fitUrl":"https://oss.coros.com/fit/447260452899012608/452780549952536578.fit","fitnessSwitch":0,"happenDate":20230614,"happenDay":20230614,"happenMonth":202306,"imageUrl":"https://map-oss-cn.coros.com/img/452780549950783489.jpg","imageUrlType":1,"isShowMs":1,"labelId":"452780549952536578","laps":0,"max2s":0,"maxSpeed":0,"mode":8,"modifyTime":1687346947,"name":"广州市 跑步","pitch":0,"rdType":0,"recalculateRecord":false,"recovery":false,"sets":0,"speedType":3,"speedValue":344,"speedValueDecimal":344.0,"sportType":100,"startLa":23.052000045776367,"startLo":113.38700103759766,"startTime":1686734599,"startTimeMs":"1686734599.33","startTimezone":32,"state":1,"step":7510,"subMode":1,"subSport":false,"taskStatus":0,"total":0,"totalAvgHr":0,"totalAvgSpeed":0,"totalDecline":21,"totalDeclineDouble":0.0,"totalElevation":16,"totalElevationDouble":0.0,"unit":2,"unitType":2,"uploadedImageData":0,"userId":447260452899012608,"uuid":"002745b8bedd0004968f0064168735e5","weatherLocationKey":"WS0E9D8WN298","weatherTime":1686733980},{"ascentDuration":0,"avgCadence":156,"avgHeartRate":157,"avgPace":333,"avgPower":213,"avgSpeed":0,"calorie":521459,"count":0,"countAvgHr":0,"countAvgSpeed":0,"createTimestamp":1686652146,"createTimezone":32,"deviceId":"COROS PACE 2 8735E5","deviceSportMode":0,"distance":6137.48,"duration":2041,"durationMs":"2041.32","endTime":1686652035,"endTimeMs":"1686652035.71","endTimezone":32,"extraType":0,"fitCreateTime":"2023-06-13 18:29:20","fitUrl":"https://oss.coros.com/fit/447260452899012608/452757237673263104.fit","fitnessSwitch":0,"happenDate":20230613,"happenDay":20230613,"happenMonth":202306,"imageUrl":"https://map-oss-cn.coros.com/img/452757237673607168.jpg","imageUrlType":1,"isShowMs":1,"labelId":"452757237673263104","laps":0,"max2s":0,"maxSpeed":0,"mode":8,"modifyTime":1687346947,"name":"广州市 跑步","pitch":0,"rdType":0,"recalculateRecord":false,"recovery":false,"sets":0,"speedType":3,"speedValue":333,"speedValueDecimal":333.0,"sportType":100,"startLa":23.038999557495117,"startLo":113.38700103759766,"startTime":1686649994,"startTimeMs":"1686649994.39","startTimezone":32,"state":1,"step":5070,"subMode":1,"subSport":false,"taskStatus":0,"total":0,"totalAvgHr":0,"totalAvgSpeed":0,"totalDecline":18,"totalDeclineDouble":0.0,"totalElevation":21,"totalElevationDouble":0.0,"unit":2,"unitType":2,"uploadedImageData":0,"userId":447260452899012608,"uuid":"00274537a60f00031d640064168735e5","weatherLocationKey":"WS0DE3FVQQJF","weatherTime":1686647674},{"ascentDuration":0,"avgCadence":160,"avgHeartRate":136,"avgPace":396,"avgPower":180,"avgSpeed":0,"calorie":102859,"count":0,"countAvgHr":0,"countAvgSpeed":0,"createTimestamp":1686651557,"createTimezone":32,"deviceId":"COROS PACE 2 8735E5","deviceSportMode":0,"distance":1274.77,"duration":504,"durationMs":"504.42","endTime":1686649028,"endTimeMs":"1686649028.75","endTimezone":32,"extraType":0,"fitCreateTime":"2023-06-13 18:19:29","fitUrl":"https://oss.coros.com/fit/447260452899012608/452757079835312129.fit","fitnessSwitch":0,"happenDate":20230613,"happenDay":20230613,"happenMonth":202306,"imageUrl":"https://map-oss-cn.coros.com/img/452757079835656192.jpg","imageUrlType":1,"isShowMs":1,"labelId":"452757079835312129","laps":0,"max2s":0,"maxSpeed":0,"mode":8,"modifyTime":1686651558,"name":"广州市 跑步","pitch":0,"rdType":0,"recalculateRecord":false,"recovery":false,"sets":0,"speedType":3,"speedValue":396,"speedValueDecimal":396.0,"sportType":100,"startLa":23.038999557495117,"startLo":113.38800048828125,"startTime":1686648449,"startTimeMs":"1686648449.64","startTimezone":32,"state":1,"step":1319,"subMode":1,"subSport":false,"taskStatus":0,"total":0,"totalAvgHr":0,"totalAvgSpeed":0,"totalDecline":25,"totalDeclineDouble":0.0,"totalElevation":19,"totalElevationDouble":0.0,"unit":2,"unitType":2,"uploadedImageData":0,"userId":447260452899012608,"uuid":"002745354aa40000e2370064168735e5","weatherLocationKey":"WS0DE3FVQQJF","weatherTime":1686647674},{"ascentDuration":0,"avgCadence":159,"avgHeartRate":166,"avgPace":318,"avgPower":227,"avgSpeed":0,"calorie":545965,"count":0,"countAvgHr":0,"countAvgSpeed":0,"createTimestamp":1686480056,"createTimezone":32,"deviceId":"COROS PACE 2 8735E5","deviceSportMode":0,"distance":6406.1,"duration":2036,"durationMs":"2035.96","endTime":1686478632,"endTimeMs":"1686478632.59","endTimezone":32,"extraType":0,"fitCreateTime":"2023-06-11 18:41:09","fitUrl":"https://oss.coros.com/fit/447260452899012608/452711042615640064.fit","fitnessSwitch":0,"happenDate":20230611,"happenDay":20230611,"happenMonth":202306,"imageUrl":"https://map-oss-cn.coros.com/img/452711042618081280.jpg","imageUrlType":1,"isShowMs":1,"labelId":"452711042615640064","laps":0,"max2s":0,"maxSpeed":0,"mode":8,"modifyTime":1686651558,"name":"广州市 其它运动","pitch":0,"rdType":0,"recalculateRecord":false,"recovery":false,"sets":0,"speedType":3,"speedValue":318,"speedValueDecimal":318.0,"sportType":100,"startLa":23.05299949645996,"startLo":113.38500213623047,"startTime":1686476531,"startTimeMs":"1686476531.39","startTimezone":32,"state":1,"step":5325,"subMode":1,"subSport":false,"taskStatus":0,"total":0,"totalAvgHr":0,"totalAvgSpeed":0,"totalDecline":14,"totalDeclineDouble":0.0,"totalElevation":12,"totalElevationDouble":0.0,"unit":2,"unitType":2,"uploadedImageData":0,"userId":447260452899012608,"uuid":"0027442ef713000334c80064168735e5","weatherLocationKey":"WS0DE3FVQQJF","weatherTime":1686474612},{"ascentDuration":0,"avgCadence":158,"avgHeartRate":160,"avgPace":323,"avgPower":221,"avgSpeed":0,"calorie":524371,"count":0,"countAvgHr":0,"countAvgSpeed":0,"createTimestamp":1686354396,"createTimezone":32,"deviceId":"COROS PACE 2 8735E5","deviceSportMode":0,"distance":6290.96,"duration":2030,"durationMs":"2029.50","endTime":1686304230,"endTimeMs":"1686304230.18","endTimezone":32,"extraType":0,"fitCreateTime":"2023-06-10 07:46:46","fitUrl":"https://oss.coros.com/fit/447260452899012608/452677311286771713.fit","fitnessSwitch":0,"happenDate":20230609,"happenDay":20230609,"happenMonth":202306,"imageUrl":"https://map-oss-cn.coros.com/img/452677311285018624.jpg","imageUrlType":1,"isShowMs":1,"labelId":"452677311286771713","laps":0,"max2s":0,"maxSpeed":0,"mode":8,"modifyTime":1686651558,"name":"广州市 其它运动","pitch":0,"rdType":0,"recalculateRecord":false,"recovery":false,"sets":0,"speedType":3,"speedValue":323,"speedValueDecimal":323.0,"sportType":100,"startLa":23.065000534057617,"startLo":113.37300109863281,"startTime":1686302200,"startTimeMs":"1686302200.68","startTimezone":32,"state":1,"step":5307,"subMode":1,"subSport":false,"taskStatus":0,"total":0,"totalAvgHr":0,"totalAvgSpeed":0,"totalDecline":13,"totalDeclineDouble":0.0,"totalElevation":15,"totalElevationDouble":0.0,"unit":2,"unitType":2,"uploadedImageData":0,"userId":447260452899012608,"uuid":"00274324f524000318c60064168735e5","weatherLocationKey":"WS0E9D8WN298","weatherTime":1686302415},{"ascentDuration":0,"avgCadence":163,"avgHeartRate":94,"avgPace":300,"avgPower":222,"avgSpeed":0,"calorie":19388,"count":0,"countAvgHr":0,"countAvgSpeed":0,"createTimestamp":1686354396,"createTimezone":32,"deviceId":"COROS PACE 2 8735E5","deviceSportMode":0,"distance":266.96,"duration":80,"durationMs":"80.10","endTime":1686302025,"endTimeMs":"1686302025.01","endTimezone":32,"extraType":0,"fitCreateTime":"2023-06-10 07:46:47","fitUrl":"https://oss.coros.com/fit/447260452899012608/452677311286771712.fit","fitnessSwitch":0,"happenDate":20230609,"happenDay":20230609,"happenMonth":202306,"imageUrl":"https://map-oss-cn.coros.com/img/452677311016583168.jpg","imageUrlType":1,"isShowMs":1,"labelId":"452677311286771712","laps":0,"max2s":0,"maxSpeed":0,"mode":8,"modifyTime":1686651558,"name":"广州市 其它运动","pitch":0,"rdType":0,"recalculateRecord":false,"recovery":false,"sets":0,"speedType":3,"speedValue":300,"speedValueDecimal":300.0,"sportType":100,"startLa":23.06399917602539,"startLo":113.37000274658203,"startTime":1686301944,"startTimeMs":"1686301944.90","startTimezone":32,"state":1,"step":213,"subMode":1,"subSport":false,"taskStatus":0,"total":0,"totalAvgHr":0,"totalAvgSpeed":0,"totalDecline":2,"totalDeclineDouble":0.0,"totalElevation":2,"totalElevationDouble":0.0,"unit":2,"unitType":2,"uploadedImageData":0,"userId":447260452899012608,"uuid":"00274324913a00001f4b0064168735e5","weatherLocationKey":"WS0E9D8WN298","weatherTime":1686302415},{"ascentDuration":0,"avgCadence":159,"avgHeartRate":161,"avgPace":314,"avgPower":225,"avgSpeed":0,"calorie":717275,"count":0,"countAvgHr":0,"countAvgSpeed":0,"createTimestamp":1686135141,"createTimezone":32,"deviceId":"COROS PACE 2 8735E5","deviceSportMode":0,"distance":8759.83,"duration":2749,"durationMs":"2748.93","endTime":1686132912,"endTimeMs":"1686132912.79","endTimezone":32,"extraType":0,"fitCreateTime":"2023-06-07 18:52:34","fitUrl":"https://oss.coros.com/fit/447260452899012608/452618455202430976.fit","fitnessSwitch":0,"happenDate":20230607,"happenDay":20230607,"happenMonth":202306,"imageUrl":"https://map-oss-cn.coros.com/img/452618455202775040.jpg","imageUrlType":1,"isShowMs":1,"labelId":"452618455202430976","laps":0,"max2s":0,"maxSpeed":0,"mode":8,"modifyTime":1686651558,"name":"广州市 其它运动","pitch":0,"rdType":0,"recalculateRecord":false,"recovery":false,"sets":0,"speedType":3,"speedValue":314,"speedValueDecimal":314.0,"sportType":100,"startLa":23.05299949645996,"startLo":113.38600158691406,"startTime":1686130163,"startTimeMs":"1686130163.85","startTimezone":32,"state":1,"step":7244,"subMode":1,"subSport":false,"taskStatus":0,"total":0,"totalAvgHr":0,"totalAvgSpeed":0,"totalDecline":13,"totalDeclineDouble":0.0,"totalElevation":13,"totalElevationDouble":0.0,"unit":2,"unitType":2,"uploadedImageData":0,"userId":447260452899012608,"uuid":"0027421e7341000431ce0064168735e5","weatherLocationKey":"WS0DE3FVQQJF","weatherTime":1686129612},{"ascentDuration":0,"avgCadence":161,"avgHeartRate":147,"avgPace":267,"avgPower":264,"avgSpeed":0,"calorie":171378,"count":0,"countAvgHr":0,"countAvgSpeed":0,"createTimestamp":1686046634,"createTimezone":32,"deviceId":"COROS PACE 2 8735E5","deviceSportMode":0,"distance":2104.5,"duration":562,"durationMs":"562.15","endTime":1686046582,"endTimeMs":"1686046582.39","endTimezone":32,"extraType":0,"fitCreateTime":"2023-06-06 18:17:24","fitUrl":"https://oss.coros.com/fit/447260452899012608/452594696785526784.fit","fitnessSwitch":0,"happenDate":20230606,"happenDay":20230606,"happenMonth":202306,"imageUrl":"https://map-oss-cn.coros.com/img/452594696785870848.jpg","imageUrlType":1,"isShowMs":1,"labelId":"452594696785526784","laps":0,"max2s":0,"maxSpeed":0,"mode":8,"modifyTime":1686651558,"name":"广州市 跑步","pitch":0,"rdType":0,"recalculateRecord":false,"recovery":false,"sets":0,"speedType":3,"speedValue":267,"speedValueDecimal":267.0,"sportType":100,"startLa":23.042999267578125,"startLo":113.38500213623047,"startTime":1686046020,"startTimeMs":"1686046020.23","startTimezone":32,"state":1,"step":1483,"subMode":1,"subSport":false,"taskStatus":0,"total":0,"totalAvgHr":0,"totalAvgSpeed":0,"totalDecline":1,"totalDeclineDouble":0.0,"totalElevation":2,"totalElevationDouble":0.0,"unit":2,"unitType":2,"uploadedImageData":0,"userId":447260452899012608,"uuid":"0027419e0ea70000db980064168735e5","weatherLocationKey":"WS0DE3FVQQJF","weatherTime":1686043211},{"ascentDuration":0,"avgCadence":157,"avgHeartRate":164,"avgPace":339,"avgPower":209,"avgSpeed":0,"calorie":1065668,"count":0,"countAvgHr":0,"countAvgSpeed":0,"createTimestamp":1685963483,"createTimezone":32,"deviceId":"COROS PACE 2 8735E5","deviceSportMode":0,"distance":12040.13,"duration":4087,"durationMs":"4087.29","endTime":1685960504,"endTimeMs":"1685960504.57","endTimezone":32,"extraType":0,"fitCreateTime":"2023-06-05 19:11:35","fitUrl":"https://oss.coros.com/fit/447260452899012608/452572376108924930.fit","fitnessSwitch":0,"happenDate":20230605,"happenDay":20230605,"happenMonth":202306,"imageUrl":"https://map-oss-cn.coros.com/img/452572376109268992.jpg","imageUrlType":1,"isShowMs":1,"labelId":"452572376108924930","laps":0,"max2s":0,"maxSpeed":0,"mode":8,"modifyTime":1685963483,"name":"广州市 跑步","pitch":0,"rdType":0,"recalculateRecord":false,"recovery":false,"sets":0,"speedType":3,"speedValue":339,"speedValueDecimal":339.0,"sportType":100,"startLa":23.059999465942383,"startLo":113.36499786376953,"startTime":1685956356,"startTimeMs":"1685956356.09","startTimezone":32,"state":1,"step":10593,"subMode":1,"subSport":false,"taskStatus":0,"total":0,"totalAvgHr":0,"totalAvgSpeed":0,"totalDecline":10,"totalDeclineDouble":0.0,"totalElevation":7,"totalElevationDouble":0.0,"unit":2,"unitType":2,"uploadedImageData":0,"userId":447260452899012608,"uuid":"002741153d99000654800064168735e5","weatherLocationKey":"WS0DE3FVQQJF","weatherTime":1685956488},{"ascentDuration":0,"avgCadence":160,"avgHeartRate":151,"avgPace":276,"avgPower":258,"avgSpeed":0,"calorie":170221,"count":0,"countAvgHr":0,"countAvgSpeed":0,"createTimestamp":1685923213,"createTimezone":32,"deviceId":"COROS PACE 2 8735E5","deviceSportMode":0,"distance":2038.11,"duration":563,"durationMs":"563.49","endTime":1685875795,"endTimeMs":"1685875795.86","endTimezone":32,"extraType":0,"fitCreateTime":"2023-06-05 08:00:26","fitUrl":"https://oss.coros.com/fit/447260452899012608/452561566213111809.fit","fitnessSwitch":0,"happenDate":20230604,"happenDay":20230604,"happenMonth":202306,"imageUrl":"https://map-oss-cn.coros.com/img/452561566213455872.jpg","imageUrlType":1,"isShowMs":1,"labelId":"452561566213111809","laps":0,"max2s":0,"maxSpeed":0,"mode":8,"modifyTime":1685923213,"name":"广州市 跑步","pitch":0,"rdType":0,"recalculateRecord":false,"recovery":false,"sets":0,"speedType":3,"speedValue":276,"speedValueDecimal":276.0,"sportType":100,"startLa":23.042999267578125,"startLo":113.38500213623047,"startTime":1685875196,"startTimeMs":"1685875196.91","startTimezone":32,"state":1,"step":1449,"subMode":1,"subSport":false,"taskStatus":0,"total":0,"totalAvgHr":0,"totalAvgSpeed":0,"totalDecline":2,"totalDeclineDouble":0.0,"totalElevation":0,"totalElevationDouble":0.0,"unit":2,"unitType":2,"uploadedImageData":0,"userId":447260452899012608,"uuid":"0027409966cb0000e9f70064168735e5","weatherLocationKey":"WS0DE3FVQQJF","weatherTime":1685873561},{"ascentDuration":0,"avgCadence":159,"avgHeartRate":158,"avgPace":298,"avgPower":238,"avgSpeed":0,"calorie":340329,"count":0,"countAvgHr":0,"countAvgSpeed":0,"createTimestamp":1685831019,"createTimezone":32,"deviceId":"COROS PACE 2 8735E5","deviceSportMode":0,"distance":4033.54,"duration":1203,"durationMs":"1203.38","endTime":1685789767,"endTimeMs":"1685789767.10","endTimezone":32,"extraType":0,"fitCreateTime":"2023-06-04 06:23:57","fitUrl":"https://oss.coros.com/fit/447260452899012608/452536818074681345.fit","fitnessSwitch":0,"happenDate":20230603,"happenDay":20230603,"happenMonth":202306,"imageUrl":"https://map-oss-cn.coros.com/img/452536818072928256.jpg","imageUrlType":1,"isShowMs":1,"labelId":"452536818074681345","laps":0,"max2s":0,"maxSpeed":0,"mode":8,"modifyTime":1685831019,"name":"广州市 跑步","pitch":0,"rdType":0,"recalculateRecord":false,"recovery":false,"sets":0,"speedType":3,"speedValue":298,"speedValueDecimal":298.0,"sportType":100,"startLa":23.042999267578125,"startLo":113.38500213623047,"startTime":1685788543,"startTimeMs":"1685788543.41","startTimezone":32,"state":1,"step":3159,"subMode":1,"subSport":false,"taskStatus":0,"total":0,"totalAvgHr":0,"totalAvgSpeed":0,"totalDecline":5,"totalDeclineDouble":0.0,"totalElevation":0,"totalElevationDouble":0.0,"unit":2,"unitType":2,"uploadedImageData":0,"userId":447260452899012608,"uuid":"002740152dc50001de010064168735e5","weatherLocationKey":"WS0DE3FVQQJF","weatherTime":1685787783},{"ascentDuration":0,"avgCadence":158,"avgHeartRate":165,"avgPace":332,"avgPower":213,"avgSpeed":0,"calorie":596590,"count":0,"countAvgHr":0,"countAvgSpeed":0,"createTimestamp":1685704415,"createTimezone":32,"deviceId":"COROS PACE 2 8735E5","deviceSportMode":0,"distance":6537.19,"duration":2170,"durationMs":"2170.47","endTime":1685702943,"endTimeMs":"1685702943.21","endTimezone":32,"extraType":0,"fitCreateTime":"2023-06-02 19:13:45","fitUrl":"https://oss.coros.com/fit/447260452899012608/452502833338548225.fit","fitnessSwitch":0,"happenDate":20230602,"happenDay":20230602,"happenMonth":202306,"imageUrl":"https://map-oss-cn.coros.com/img/452502833338892288.jpg","imageUrlType":1,"isShowMs":1,"labelId":"452502833338548225","laps":0,"max2s":0,"maxSpeed":0,"mode":8,"modifyTime":1685704415,"name":"广州市 跑步","pitch":0,"rdType":0,"recalculateRecord":false,"recovery":false,"sets":0,"speedType":3,"speedValue":332,"speedValueDecimal":332.0,"sportType":100,"startLa":23.05299949645996,"startLo":113.38600158691406,"startTime":1685700772,"startTimeMs":"1685700772.74","startTimezone":32,"state":1,"step":5632,"subMode":1,"subSport":false,"taskStatus":0,"total":0,"totalAvgHr":0,"totalAvgSpeed":0,"totalDecline":11,"totalDeclineDouble":0.0,"totalElevation":9,"totalElevationDouble":0.0,"unit":2,"unitType":2,"uploadedImageData":0,"userId":447260452899012608,"uuid":"00273f8f405a00034fd70064168735e5","weatherLocationKey":"WS0DE3FVQQJF","weatherTime":1685701513},{"ascentDuration":0,"avgCadence":156,"avgHeartRate":130,"avgPace":314,"avgPower":228,"avgSpeed":0,"calorie":165879,"count":0,"countAvgHr":0,"countAvgSpeed":0,"createTimestamp":1685704415,"createTimezone":32,"deviceId":"COROS PACE 2 8735E5","deviceSportMode":0,"distance":2053.4,"duration":645,"durationMs":"645.01","endTime":1685611593,"endTimeMs":"1685611593.61","endTimezone":32,"extraType":0,"fitCreateTime":"2023-06-02 19:13:45","fitUrl":"https://oss.coros.com/fit/447260452899012608/452502833070112769.fit","fitnessSwitch":0,"happenDate":20230601,"happenDay":20230601,"happenMonth":202306,"imageUrl":"https://map-oss-cn.coros.com/img/452502833072553984.jpg","imageUrlType":1,"isShowMs":1,"labelId":"452502833070112769","laps":0,"max2s":0,"maxSpeed":0,"mode":8,"modifyTime":1685704416,"name":"广州市 跑步","pitch":0,"rdType":0,"recalculateRecord":false,"recovery":false,"sets":0,"speedType":3,"speedValue":314,"speedValueDecimal":314.0,"sportType":100,"startLa":23.042999267578125,"startLo":113.38500213623047,"startTime":1685610948,"startTimeMs":"1685610948.59","startTimezone":32,"state":1,"step":1657,"subMode":1,"subSport":false,"taskStatus":0,"total":0,"totalAvgHr":0,"totalAvgSpeed":0,"totalDecline":4,"totalDeclineDouble":0.0,"totalElevation":5,"totalElevationDouble":0.0,"unit":2,"unitType":2,"uploadedImageData":0,"userId":447260452899012608,"uuid":"00273f0630cb0000fbf60064168735e5","weatherLocationKey":"WS0DE3FVQQJF","weatherTime":1685611211}],"message":"成功","result":"0000","tLogId":"39111098369953492246528"}