{"apiCode":"B7D57DB7","data":[{"ascentDuration":0,"avgCadence":160,"avgHeartRate":156,"avgPace":324,"avgPower":217,"avgSpeed":0,"calorie":493242,"count":0,"countAvgHr":0,"countAvgSpeed":0,"createTimestamp":1706694700,"createTimezone":32,"deviceId":"COROS PACE 2 8735E5","deviceSportMode":0,"distance":6022.19,"distanceStatistics":0,"duration":1948,"durationMs":"1948.28","endTime":1706693938,"endTimeMs":"1706693938.58","endTimezone":32,"extraType":0,"fastKmV2":0,"filter":0,"fitCreateTime":"2024-01-31 17:51:53","fitUrl":"https://oss.coros.com/fit/447260452899012608/458137369795657730.fit","fitnessSwitch":0,"floors":0,"happenDate":20240131,"happenDay":20240131,"happenMonth":202401,"imageUrl":"https://map-oss-cn.coros.com/img/458137369798098945.jpg","imageUrlType":1,"isShowMs":1,"labelId":"458137369795657730","laps":0,"max2s":0,"maxSpeed":0,"mode":8,"modifyTime":1707384455,"name":"惠州市 跑步","pitch":0,"rdType":0,"recalculateRecord":false,"recovery":false,"sets":0,"speedType":3,"speedValue":324,"speedValueDecimal":324.0,"sportType":100,"startLa":22.875999450683594,"startLo":114.33200073242188,"startTime":1706691445,"startTimeMs":"1706691445.32","startTimezone":32,"state":1,"step":5053,"subMode":1,"subSport":false,"taskStatus":0,"total":0,"totalAvgHr":0,"totalAvgSpeed":0,"totalDecline":5,"totalDeclineDouble":0.0,"totalElevation":2,"totalElevationDouble":0.0,"unit":2,"unitType":2,"uploadedImageData":0,"userId":447260452899012608,"uuid":"0027bcac79d40003cdee0064168735e5","weatherLocationKey":"WS13SYDE8K43","weatherTime":1706689427},{"ascentDuration":0,"avgCadence":162,"avgHeartRate":116,"avgPace":258,"avgPower":255,"avgSpeed":0,"calorie":52885,"count":0,"countAvgHr":0,"countAvgSpeed":0,"createTimestamp":1706519548,"createTimezone":32,"deviceId":"COROS PACE 2 8735E5","deviceSportMode":0,"distance":753.38,"distanceStatistics":0,"duration":194,"durationMs":"194.13","endTime":1706518390,"endTimeMs":"1706518390.33","endTimezone":32,"extraType":0,"fastKmV2":0,"filter":0,"fitCreateTime":"2024-01-29 17:12:42","fitUrl":"https://oss.coros.com/fit/447260452899012608/458090352790765568.fit","fitnessSwitch":0,"floors":0,"happenDate":20240129,"happenDay":20240129,"happenMonth":202401,"imageUrl":"https://map-oss-cn.coros.com/img/458090353057447936.jpg","imageUrlType":1,"isShowMs":1,"labelId":"458090352790765568","laps":0,"max2s":0,"maxSpeed":0,"mode":8,"modifyTime":1706519548,"name":"惠州市 跑步","pitch":0,"rdType":0,"recalculateRecord":false,"recovery":false,"sets":0,"speedType":3,"speedValue":258,"speedValueDecimal":258.0,"sportType":100,"startLa":22.875999450683594,"startLo":114.33200073242188,"startTime":1706517857,"startTimeMs":"1706517857.06","startTimezone":32,"state":1,"step":518,"subMode":1,"subSport":false,"taskStatus":0,"total":0,"totalAvgHr":0,"totalAvgSpeed":0,"totalDecline":0,"totalDeclineDouble":0.0,"totalElevation":0,"totalElevationDouble":0.0,"unit":2,"unitType":2,"uploadedImageData":0,"userId":447260452899012608,"uuid":"0027bba399ea0000d04f0064168735e5","weatherLocationKey":"WS13SYDE8K43","weatherTime":1706516054},{"ascentDuration":0,"avgCadence":159,"avgHeartRate":148,"avgPace":337,"avgPower":207,"avgSpeed":0,"calorie":597699,"count":0,"countAvgHr":0,"countAvgSpeed":0,"createTimestamp":1706434181,"createTimezone":32,"deviceId":"COROS PACE 2 8735E5","deviceSportMode":0,"distance":7490.32,"distanceStatistics":0,"duration":2528,"durationMs":"2527.85","endTime":1706434067,"endTimeMs":"1706434067.13","endTimezone":32,"extraType":0,"fastKmV2":0,"filter":0,"fitCreateTime":"2024-01-28 17:29:51","fitUrl":"https://oss.coros.com/fit/447260452899012608/458067437527531520.fit","fitnessSwitch":0,"floors":0,"happenDate":20240128,"happenDay":20240128,"happenMonth":202401,"imageUrl":"https://map-oss-cn.coros.com/img/458067437529972736.jpg","imageUrlType":1,"isShowMs":1,"labelId":"458067437527531520","laps":0,"max2s":0,"maxSpeed":0,"mode":8,"modifyTime":1706434183,"name":"惠州市 跑步","pitch":0,"rdType":0,"recalculateRecord":false,"recovery":false,"sets":0,"speedType":3,"speedValue":337,"speedValueDecimal":337.0,"sportType":100,"startLa":22.875999450683594,"startLo":114.33200073242188,"startTime":1706430065,"startTimeMs":"1706430065.30","startTimezone":32,"state":1,"step":6400,"subMode":1,"subSport":false,"taskStatus":0,"total":0,"totalAvgHr":0,"totalAvgSpeed":0,"totalDecline":10,"totalDeclineDouble":0.0,"totalElevation":2,"totalElevationDouble":0.0,"unit":2,"unitType":2,"uploadedImageData":0,"userId":447260452899012608,"uuid":"0027bb1da44200061b370064168735e5","weatherLocationKey":"WS13SYDE8K43","weatherTime":1706430301},{"ascentDuration":0,"avgCadence":159,"avgHeartRate":152,"avgPace":338,"avgPower":205,"avgSpeed":0,"calorie":486237,"count":0,"countAvgHr":0,"countAvgSpeed":0,"createTimestamp":1706175346,"createTimezone":32,"deviceId":"COROS PACE 2 8735E5","deviceSportMode":0,"distance":6038.11,"distanceStatistics":0,"duration":2042,"durationMs":"2041.67","endTime":1706175322,"endTimeMs":"1706175322.82","endTimezone":32,"extraType":0,"fastKmV2":0,"filter":0,"fitCreateTime":"2024-01-25 17:36:05","fitUrl":"https://oss.coros.com/fit/447260452899012608/457997956769939457.fit","fitnessSwitch":0,"floors":0,"happenDate":20240125,"happenDay":20240125,"happenMonth":202401,"imageUrl":"https://map-oss-cn.coros.com/img/457997956768186368.jpg","imageUrlType":1,"isShowMs":1,"labelId":"457997956769939457","laps":0,"max2s":0,"maxSpeed":0,"mode":8,"modifyTime":1706434183,"name":"惠州市 其它运动","pitch":0,"rdType":0,"recalculateRecord":false,"recovery":false,"sets":0,"speedType":3,"speedValue":338,"speedValueDecimal":338.0,"sportType":100,"startLa":22.875999450683594,"startLo":114.33200073242188,"startTime":1706172439,"startTimeMs":"1706172439.91","startTimezone":32,"state":1,"step":5328,"subMode":1,"subSport":false,"taskStatus":0,"total":0,"totalAvgHr":0,"totalAvgSpeed":0,"totalDecline":3,"totalDeclineDouble":0.0,"totalElevation":0,"totalElevationDouble":0.0,"unit":2,"unitType":2,"uploadedImageData":0,"userId":447260452899012608,"uuid":"0027b9948957000466230064168735e5","weatherLocationKey":"WS13SYDE8K43","weatherTime":1706170923},{"ascentDuration":0,"avgCadence":161,"avgHeartRate":142,"avgPace":347,"avgPower":198,"avgSpeed":0,"calorie":322007,"count":0,"countAvgHr":0,"countAvgSpeed":0,"createTimestamp":1706090801,"createTimezone":32,"deviceId":"COROS PACE 2 8735E5","deviceSportMode":0,"distance":4024.21,"distanceStatistics":0,"duration":1397,"durationMs":"1397.26","endTime":1706090776,"endTimeMs":"1706090776.11","endTimezone":32,"extraType":0,"fastKmV2":0,"filter":0,"fitCreateTime":"2024-01-24 18:06:54","fitUrl":"https://oss.coros.com/fit/447260452899012608/457975261894311937.fit","fitnessSwitch":0,"floors":0,"happenDate":20240124,"happenDay":20240124,"happenMonth":202401,"imageUrl":"https://map-oss-cn.coros.com/img/457975262163091456.jpg","imageUrlType":1,"isShowMs":1,"labelId":"457975261894311937","laps":0,"max2s":0,"maxSpeed":0,"mode":8,"modifyTime":1706434183,"name":"惠州市 跑步","pitch":0,"rdType":0,"recalculateRecord":false,"recovery":false,"sets":0,"speedType":3,"speedValue":347,"speedValueDecimal":347.0,"sportType":100,"startLa":22.868000030517578,"startLo":114.33300018310547,"startTime":1706088768,"startTimeMs":"1706088768.94","startTimezone":32,"state":1,"step":3669,"subMode":1,"subSport":false,"taskStatus":0,"total":0,"totalAvgHr":0,"totalAvgSpeed":0,"totalDecline":7,"totalDeclineDouble":0.0,"totalElevation":3,"totalElevationDouble":0.0,"unit":2,"unitType":2,"uploadedImageData":0,"userId":447260452899012608,"uuid":"0027b914dd5e0003100d0064168735e5","weatherLocationKey":"WS13SYDE8K43","weatherTime":1706087711},{"ascentDuration":0,"avgCadence":0,"avgHeartRate":134,"avgPace":0,"avgPower":0,"avgSpeed":2299,"calorie":771207,"count":0,"countAvgHr":0,"countAvgSpeed":0,"createTimestamp":1705918340,"createTimezone":32,"deviceId":"COROS PACE 2 8735E5","deviceSportMode":0,"distance":35409.4,"distanceStatistics":0,"duration":5544,"durationMs":"5544.15","endTime":1705918289,"endTimeMs":"1705918289.67","endTimezone":32,"extraType":0,"fastKmV2":0,"filter":0,"fitCreateTime":"2024-01-22 18:12:40","fitUrl":"https://oss.coros.com/fit/447260452899012608/457928967515570177.fit","fitnessSwitch":0,"floors":0,"happenDate":20240122,"happenDay":20240122,"happenMonth":202401,"imageUrl":"https://map-oss-cn.coros.com/img/457928967515914240.jpg","imageUrlType":1,"isShowMs":1,"labelId":"457928967515570177","laps":0,"max2s":0,"maxSpeed":4053,"mode":9,"modifyTime":1706434183,"name":"惠州市 骑行","pitch":0,"rdType":0,"recalculateRecord":false,"recovery":false,"sets":0,"speedType":1,"speedValue":2299,"speedValueDecimal":2299.0,"sportType":200,"startLa":22.86199951171875,"startLo":114.34400177001953,"startTime":1705911427,"startTimeMs":"1705911427.91","startTimezone":32,"state":1,"step":0,"subMode":1,"subSport":false,"taskStatus":0,"total":0,"totalAvgHr":0,"totalAvgSpeed":0,"totalDecline":180,"totalDeclineDouble":0.0,"totalElevation":165,"totalElevationDouble":0.0,"unit":2,"unitType":2,"uploadedImageData":0,"userId":447260452899012608,"uuid":"0027b8064387000a786000c8168735e5","weatherLocationKey":"WS13SYDE8K43","weatherTime":1705911864},{"ascentDuration":0,"avgCadence":160,"avgHeartRate":135,"avgPace":346,"avgPower":201,"avgSpeed":0,"calorie":315223,"count":0,"countAvgHr":0,"countAvgSpeed":0,"createTimestamp":1705833107,"createTimezone":32,"deviceId":"COROS PACE 2 8735E5","deviceSportMode":0,"distance":4022.2,"distanceStatistics":0,"duration":1390,"durationMs":"1389.76","endTime":1705833076,"endTimeMs":"1705833076.33","endTimezone":32,"extraType":0,"fastKmV2":0,"filter":0,"fitCreateTime":"2024-01-21 18:32:01","fitUrl":"https://oss.coros.com/fit/447260452899012608/457906087687913474.fit","fitnessSwitch":0,"floors":0,"happenDate":20240121,"happenDay":20240121,"happenMonth":202401,"imageUrl":"https://map-oss-cn.coros.com/img/457906087688257537.jpg","imageUrlType":1,"isShowMs":1,"labelId":"457906087687913474","laps":0,"max2s":0,"maxSpeed":0,"mode":8,"modifyTime":1706434183,"name":"惠州市 跑步","pitch":0,"rdType":0,"recalculateRecord":false,"recovery":false,"sets":0,"speedType":3,"speedValue":346,"speedValueDecimal":346.0,"sportType":100,"startLa":22.868000030517578,"startLo":114.33200073242188,"startTime":1705830433,"startTimeMs":"1705830433.82","startTimezone":32,"state":1,"step":3662,"subMode":1,"subSport":false,"taskStatus":0,"total":0,"totalAvgHr":0,"totalAvgSpeed":0,"totalDecline":6,"totalDeclineDouble":0.0,"totalElevation":2,"totalElevationDouble":0.0,"unit":2,"unitType":2,"uploadedImageData":0,"userId":447260452899012608,"uuid":"0027b78aad360004083b0064168735e5","weatherLocationKey":"WS13SYDE8K43","weatherTime":1705828513},{"ascentDuration":0,"avgCadence":0,"avgHeartRate":125,"avgPace":0,"avgPower":0,"avgSpeed":2191,"calorie":373369,"count":0,"countAvgHr":0,"countAvgSpeed":0,"createTimestamp":1705659838,"createTimezone":32,"deviceId":"COROS PACE 2 8735E5","deviceSportMode":0,"distance":18285.39,"distanceStatistics":0,"duration":3004,"durationMs":"3004.21","endTime":1705659793,"endTimeMs":"1705659793.53","endTimezone":32,"extraType":0,"fastKmV2":0,"filter":0,"fitCreateTime":"2024-01-19 18:24:08","fitUrl":"https://oss.coros.com/fit/447260452899012608/457859576413323264.fit","fitnessSwitch":0,"floors":0,"happenDate":20240119,"happenDay":20240119,"happenMonth":202401,"imageUrl":"https://map-oss-cn.coros.com/img/457859576411570176.jpg","imageUrlType":1,"isShowMs":1,"labelId":"457859576413323264","laps":0,"max2s":0,"maxSpeed":3710,"mode":9,"modifyTime":1706434183,"name":"惠州市 骑行","pitch":0,"rdType":0,"recalculateRecord":false,"recovery":false,"sets":0,"speedType":1,"speedValue":2191,"speedValueDecimal":2191.0,"sportType":200,"startLa":23.023000717163086,"startLo":114.36100006103516,"startTime":1705656462,"startTimeMs":"1705656462.23","startTimezone":32,"state":1,"step":0,"subMode":1,"subSport":false,"taskStatus":0,"total":0,"totalAvgHr":0,"totalAvgSpeed":0,"totalDecline":90,"totalDeclineDouble":0.0,"totalElevation":113,"totalElevationDouble":0.0,"unit":2,"unitType":2,"uploadedImageData":0,"userId":447260452899012608,"uuid":"0027b681378f0005154a00c8168735e5","weatherLocationKey":"WS13SYDE8K43","weatherTime":1705655711},{"ascentDuration":0,"avgCadence":158,"avgHeartRate":148,"avgPace":337,"avgPower":209,"avgSpeed":0,"calorie":175456,"count":0,"countAvgHr":0,"countAvgSpeed":0,"createTimestamp":1705568865,"createTimezone":32,"deviceId":"COROS PACE 2 8735E5","deviceSportMode":0,"distance":2148.37,"distanceStatistics":0,"duration":725,"durationMs":"725.04","endTime":1705568822,"endTimeMs":"1705568822.14","endTimezone":32,"extraType":0,"fastKmV2":0,"filter":0,"fitCreateTime":"2024-01-18 17:08:10","fitUrl":"https://oss.coros.com/fit/447260452899012608/457835155766149120.fit","fitnessSwitch":0,"floors":0,"happenDate":20240118,"happenDay":20240118,"happenMonth":202401,"imageUrl":"https://map-oss-cn.coros.com/img/457835155766493184.jpg","imageUrlType":1,"isShowMs":1,"labelId":"457835155766149120","laps":0,"max2s":0,"maxSpeed":0,"mode":8,"modifyTime":1706434183,"name":"广州市 跑步","pitch":0,"rdType":0,"recalculateRecord":false,"recovery":false,"sets":0,"speedType":3,"speedValue":337,"speedValueDecimal":337.0,"sportType":100,"startLa":23.038999557495117,"startLo":113.38700103759766,"startTime":1705567881,"startTimeMs":"1705567881.74","startTimezone":32,"state":1,"step":1872,"subMode":1,"subSport":false,"taskStatus":0,"total":0,"totalAvgHr":0,"totalAvgSpeed":0,"totalDecline":1,"totalDeclineDouble":0.0,"totalElevation":0,"totalElevationDouble":0.0,"unit":2,"unitType":2,"uploadedImageData":0,"userId":447260452899012608,"uuid":"0027b5fa0dce00016f580064168735e5","weatherLocationKey":"WS0DE3FVQQJF","weatherTime":1705566011},{"ascentDuration":0,"avgCadence":158,"avgHeartRate":153,"avgPace":342,"avgPower":207,"avgSpeed":0,"calorie":654788,"count":0,"countAvgHr":0,"countAvgSpeed":0,"createTimestamp":1705398337,"createTimezone":32,"deviceId":"COROS PACE 2 8735E5","deviceSportMode":0,"distance":8023.14,"distanceStatistics":0,"duration":2742,"durationMs":"2741.51","endTime":1705398284,"endTimeMs":"1705398284.20","endTimezone":32,"extraType":0,"fastKmV2":0,"filter":0,"fitCreateTime":"2024-01-16 17:45:53","fitUrl":"https://oss.coros.com/fit/447260452899012608/457789380002611201.fit","fitnessSwitch":0,"floors":0,"happenDate":20240116,"happenDay":20240116,"happenMonth":202401,"imageUrl":"https://map-oss-cn.coros.com/img/457789380271390720.jpg","imageUrlType":1,"isShowMs":1,"labelId":"457789380002611201","laps":0,"max2s":0,"maxSpeed":0,"mode":8,"modifyTime":1706434183,"name":"广州市 跑步","pitch":0,"rdType":0,"recalculateRecord":false,"recovery":false,"sets":0,"speedType":3,"speedValue":342,"speedValueDecimal":342.0,"sportType":100,"startLa":23.03700065612793,"startLo":113.37999725341797,"startTime":1705395140,"startTimeMs":"1705395140.23","startTimezone":32,"state":1,"step":7168,"subMode":1,"subSport":false,"taskStatus":0,"total":0,"totalAvgHr":0,"totalAvgSpeed":0,"totalDecline":7,"totalDeclineDouble":0.0,"totalElevation":2,"totalElevationDouble":0.0,"unit":2,"unitType":2,"uploadedImageData":0,"userId":447260452899012608,"uuid":"0027b4f278a70004cc1d0064168735e5","weatherLocationKey":"WS0DE3FVQQJF","weatherTime":1705393467},{"ascentDuration":0,"avgCadence":159,"avgHeartRate":150,"avgPace":332,"avgPower":212,"avgSpeed":0,"calorie":492270,"count":0,"countAvgHr":0,"countAvgSpeed":0,"createTimestamp":1705227643,"createTimezone":32,"deviceId":"COROS PACE 2 8735E5","deviceSportMode":0,"distance":6031.82,"distanceStatistics":0,"duration":2005,"durationMs":"2005.00","endTime":1705227230,"endTimeMs":"1705227230.43","endTimezone":32,"extraType":0,"fastKmV2":0,"filter":0,"fitCreateTime":"2024-01-14 18:21:02","fitUrl":"https://oss.coros.com/fit/447260452899012608/457743559680884737.fit","fitnessSwitch":0,"floors":0,"happenDate":20240114,"happenDay":20240114,"happenMonth":202401,"imageUrl":"https://map-oss-cn.coros.com/img/457743559683325953.jpg","imageUrlType":1,"isShowMs":1,"labelId":"457743559680884737","laps":0,"max2s":0,"maxSpeed":0,"mode":8,"modifyTime":1705246034,"name":"广州市 跑步","pitch":0,"rdType":0,"recalculateRecord":false,"recovery":false,"sets":0,"speedType":3,"speedValue":332,"speedValueDecimal":332.0,"sportType":100,"startLa":23.03700065612793,"startLo":113.37899780273438,"startTime":1705224795,"startTimeMs":"1705224795.71","startTimezone":32,"state":1,"step":5311,"subMode":1,"subSport":false,"taskStatus":0,"total":0,"totalAvgHr":0,"totalAvgSpeed":0,"totalDecline":5,"totalDeclineDouble":0.0,"totalElevation":0,"totalElevationDouble":0.0,"unit":2,"unitType":2,"uploadedImageData":0,"userId":447260452899012608,"uuid":"0027b3ee8bd30003b7100064168735e5","weatherLocationKey":"WS0DE3FVQQJF","weatherTime":1705223813},{"ascentDuration":0,"avgCadence":158,"avgHeartRate":120,"avgPace":343,"avgPower":209,"avgSpeed":0,"calorie":33697,"count":0,"countAvgHr":0,"countAvgSpeed":0,"createTimestamp":1705062994,"createTimezone":32,"deviceId":"COROS PACE 2 8735E5","deviceSportMode":0,"distance":426.62,"distanceStatistics":0,"duration":146,"durationMs":"146.21","endTime":1705054510,"endTimeMs":"1705054510.83","endTimezone":32,"extraType":0,"fastKmV2":0,"filter":0,"fitCreateTime":"2024-01-12 20:36:46","fitUrl":"https://oss.coros.com/fit/447260452899012608/457699362319925248.fit","fitnessSwitch":0,"floors":0,"happenDate":20240112,"happenDay":20240112,"happenMonth":202401,"imageUrl":"https://map-oss-cn.coros.com/img/457699362320269312.jpg","imageUrlType":1,"isShowMs":1,"labelId":"457699362319925248","laps":0,"max2s":0,"maxSpeed":0,"mode":8,"modifyTime":1705062995,"name":"广州市 跑步","pitch":0,"rdType":0,"recalculateRecord":false,"recovery":false,"sets":0,"speedType":3,"speedValue":343,"speedValueDecimal":343.0,"sportType":100,"startLa":23.038999557495117,"startLo":113.38700103759766,"startTime":1705054364,"startTimeMs":"1705054364.62","startTimezone":32,"state":1,"step":367,"subMode":1,"subSport":false,"taskStatus":0,"total":0,"totalAvgHr":0,"totalAvgSpeed":0,"totalDecline":0,"totalDeclineDouble":0.0,"totalElevation":0,"totalElevationDouble":0.0,"unit":2,"unitType":2,"uploadedImageData":0,"userId":447260452899012608,"uuid":"0027b2ea7d2e0000391d0064168735e5","weatherLocationKey":"WS0DE3FVQQJF","weatherTime":1705054810},{"ascentDuration":0,"avgCadence":159,"avgHeartRate":104,"avgPace":329,"avgPower":219,"avgSpeed":0,"calorie":44521,"count":0,"countAvgHr":0,"countAvgSpeed":0,"createTimestamp":1705054321,"createTimezone":32,"deviceId":"COROS PACE 2 8735E5","deviceSportMode":0,"distance":565.82,"distanceStatistics":0,"duration":186,"durationMs":"186.16","endTime":1705054180,"endTimeMs":"1705054180.59","endTimezone":32,"extraType":0,"fastKmV2":0,"filter":0,"fitCreateTime":"2024-01-12 18:12:23","fitUrl":"https://oss.coros.com/fit/447260452899012608/457697034181312512.fit","fitnessSwitch":0,"floors":0,"happenDate":20240112,"happenDay":20240112,"happenMonth":202401,"imageUrl":"https://map-oss-cn.coros.com/img/457697034179559425.jpg","imageUrlType":1,"isShowMs":1,"labelId":"457697034181312512","laps":0,"max2s":0,"maxSpeed":0,"mode":8,"modifyTime":1705062995,"name":"广州市 其它运动","pitch":0,"rdType":0,"recalculateRecord":false,"recovery":false,"sets":0,"speedType":3,"speedValue":329,"speedValueDecimal":329.0,"sportType":100,"startLa":23.038000106811523,"startLo":113.38800048828125,"startTime":1705053994,"startTimeMs":"1705053994.43","startTimezone":32,"state":1,"step":485,"subMode":1,"subSport":false,"taskStatus":0,"total":0,"totalAvgHr":0,"totalAvgSpeed":0,"totalDecline":0,"totalDeclineDouble":0.0,"totalElevation":0,"totalElevationDouble":0.0,"unit":2,"unitType":2,"uploadedImageData":0,"userId":447260452899012608,"uuid":"0027b2e9ec93000048b80064168735e5","weatherLocationKey":"WS0DE3FVQQJF","weatherTime":1705051210},{"ascentDuration":0,"avgCadence":159,"avgHeartRate":155,"avgPace":335,"avgPower":211,"avgSpeed":0,"calorie":813349,"count":0,"countAvgHr":0,"countAvgSpeed":0,"createTimestamp":1704968684,"createTimezone":32,"deviceId":"COROS PACE 2 8735E5","deviceSportMode":0,"distance":10018.5,"distanceStatistics":0,"duration":3358,"durationMs":"3357.65","endTime":1704968517,"endTimeMs":"1704968517.41","endTimezone":32,"extraType":0,"fastKmV2":0,"filter":0,"fitCreateTime":"2024-01-11 18:25:00","fitUrl":"https://oss.coros.com/fit/447260452899012608/457674046172069888.fit","fitnessSwitch":0,"floors":0,"happenDate":20240111,"happenDay":20240111,"happenMonth":202401,"imageUrl":"https://map-oss-cn.coros.com/img/457674046172413952.jpg","imageUrlType":1,"isShowMs":1,"labelId":"457674046172069888","laps":0,"max2s":0,"maxSpeed":0,"mode":8,"modifyTime":1705062995,"name":"广州市 跑步","pitch":0,"rdType":0,"recalculateRecord":false,"recovery":false,"sets":0,"speedType":3,"speedValue":335,"speedValueDecimal":335.0,"sportType":100,"startLa":23.038999557495117,"startLo":113.38700103759766,"startTime":1704964430,"startTimeMs":"1704964430.66","startTimezone":32,"state":1,"step":8771,"subMode":1,"subSport":false,"taskStatus":0,"total":0,"totalAvgHr":0,"totalAvgSpeed":0,"totalDecline":6,"totalDeclineDouble":0.0,"totalElevation":5,"totalElevationDouble":0.0,"unit":2,"unitType":2,"uploadedImageData":0,"userId":447260452899012608,"uuid":"0027b26142ba00063c630064168735e5","weatherLocationKey":"WS0DE3FVQQJF","weatherTime":1704964614},{"ascentDuration":0,"avgCadence":159,"avgHeartRate":154,"avgPace":317,"avgPower":222,"avgSpeed":0,"calorie":324810,"count":0,"countAvgHr":0,"countAvgSpeed":0,"createTimestamp":1704882016,"createTimezone":32,"deviceId":"COROS PACE 2 8735E5","deviceSportMode":0,"distance":4026.64,"distanceStatistics":0,"duration":1276,"durationMs":"1275.65","endTime":1704880913,"endTimeMs":"1704880913.45","endTimezone":32,"extraType":0,"fastKmV2":0,"filter":0,"fitCreateTime":"2024-01-10 18:20:31","fitUrl":"https://oss.coros.com/fit/447260452899012608/457650781407969281.fit","fitnessSwitch":0,"floors":0,"happenDate":20240110,"happenDay":20240110,"happenMonth":202401,"imageUrl":"https://map-oss-cn.coros.com/img/457650781410410496.jpg","imageUrlType":1,"isShowMs":1,"labelId":"457650781407969281","laps":0,"max2s":0,"maxSpeed":0,"mode":8,"modifyTime":1705062995,"name":"广州市 跑步","pitch":0,"rdType":0,"recalculateRecord":false,"recovery":false,"sets":0,"speedType":3,"speedValue":317,"speedValueDecimal":317.0,"sportType":100,"startLa":23.038999557495117,"startLo":113.38700103759766,"startTime":1704879476,"startTimeMs":"1704879476.88","startTimezone":32,"state":1,"step":3352,"subMode":1,"subSport":false,"taskStatus":0,"total":0,"totalAvgHr":0,"totalAvgSpeed":0,"totalDecline":5,"totalDeclineDouble":0.0,"totalElevation":0,"totalElevationDouble":0.0,"unit":2,"unitType":2,"uploadedImageData":0,"userId":447260452899012608,"uuid":"0027b1dfa1a8000231290064168735e5","weatherLocationKey":"WS0DE3FVQQJF","weatherTime":1704878673},{"ascentDuration":0,"avgCadence":157,"avgHeartRate":154,"avgPace":331,"avgPower":212,"avgSpeed":0,"calorie":810062,"count":0,"countAvgHr":0,"countAvgSpeed":0,"createTimestamp":1704710627,"createTimezone":32,"deviceId":"COROS PACE 2 8735E5","deviceSportMode":0,"distance":10031.26,"distanceStatistics":0,"duration":3324,"durationMs":"3323.51","endTime":1704710449,"endTimeMs":"1704710449.34","endTimezone":32,"extraType":0,"fastKmV2":0,"filter":0,"fitCreateTime":"2024-01-08 18:44:13","fitUrl":"https://oss.coros.com/fit/447260452899012608/457604774525698048.fit","fitnessSwitch":0,"floors":0,"happenDate":20240108,"happenDay":20240108,"happenMonth":202401,"imageUrl":"https://map-oss-cn.coros.com/img/457604774526042112.jpg","imageUrlType":1,"isShowMs":1,"labelId":"457604774525698048","laps":0,"max2s":0,"maxSpeed":0,"mode":8,"modifyTime":1704710628,"name":"广州市 跑步","pitch":0,"rdType":0,"recalculateRecord":false,"recovery":false,"sets":0,"speedType":3,"speedValue":331,"speedValueDecimal":331.0,"sportType":100,"startLa":23.038999557495117,"startLo":113.38700103759766,"startTime":1704706376,"startTimeMs":"1704706376.71","startTimezone":32,"state":1,"step":8531,"subMode":1,"subSport":false,"taskStatus":0,"total":0,"totalAvgHr":0,"totalAvgSpeed":0,"totalDecline":8,"totalDeclineDouble":0.0,"totalElevation":0,"totalElevationDouble":0.0,"unit":2,"unitType":2,"uploadedImageData":0,"userId":447260452899012608,"uuid":"0027b0d78067000636df0064168735e5","weatherLocationKey":"WS0DE3FVQQJF","weatherTime":1704705262},{"ascentDuration":0,"avgCadence":159,"avgHeartRate":153,"avgPace":331,"avgPower":214,"avgSpeed":0,"calorie":480134,"count":0,"countAvgHr":0,"countAvgSpeed":0,"createTimestamp":1704533251,"createTimezone":32,"deviceId":"COROS PACE 2 8735E5","deviceSportMode":0,"distance":6021.39,"distanceStatistics":0,"duration":1992,"durationMs":"1991.70","endTime":1704532800,"endTimeMs":"1704532800.91","endTimezone":32,"extraType":0,"fastKmV2":0,"filter":0,"fitCreateTime":"2024-01-06 17:27:42","fitUrl":"https://oss.coros.com/fit/447260452899012608/457557160249819136.fit","fitnessSwitch":0,"floors":0,"happenDate":20240106,"happenDay":20240106,"happenMonth":202401,"imageUrl":"https://map-oss-cn.coros.com/img/457557160250163200.jpg","imageUrlType":1,"isShowMs":1,"labelId":"457557160249819136","laps":0,"max2s":0,"maxSpeed":0,"mode":8,"modifyTime":1704533251,"name":"广州市 跑步","pitch":0,"rdType":0,"recalculateRecord":false,"recovery":false,"sets":0,"speedType":3,"speedValue":331,"speedValueDecimal":331.0,"sportType":100,"startLa":23.038999557495117,"startLo":113.38700103759766,"startTime":1704530448,"startTimeMs":"1704530448.38","startTimezone":32,"state":1,"step":5202,"subMode":1,"subSport":false,"taskStatus":0,"total":0,"totalAvgHr":0,"totalAvgSpeed":0,"totalDecline":2,"totalDeclineDouble":0.0,"totalElevation":0,"totalElevationDouble":0.0,"unit":2,"unitType":2,"uploadedImageData":0,"userId":447260452899012608,"uuid":"0027afcb0e66000396f50064168735e5","weatherLocationKey":"WS0DE3FVQQJF","weatherTime":1704529467},{"ascentDuration":0,"avgCadence":158,"avgHeartRate":156,"avgPace":327,"avgPower":217,"avgSpeed":0,"calorie":563453,"count":0,"countAvgHr":0,"countAvgSpeed":0,"createTimestamp":1704448042,"createTimezone":32,"deviceId":"COROS PACE 2 8735E5","deviceSportMode":0,"distance":7024.34,"distanceStatistics":0,"duration":2295,"durationMs":"2294.69","endTime":1704447692,"endTimeMs":"1704447692.25","endTimezone":32,"extraType":0,"fastKmV2":0,"filter":0,"fitCreateTime":"2024-01-05 17:47:34","fitUrl":"https://oss.coros.com/fit/447260452899012608/457534287130951680.fit","fitnessSwitch":0,"floors":0,"happenDate":20240105,"happenDay":20240105,"happenMonth":202401,"imageUrl":"https://map-oss-cn.coros.com/img/457534287133392896.jpg","imageUrlType":1,"isShowMs":1,"labelId":"457534287130951680","laps":0,"max2s":0,"maxSpeed":0,"mode":8,"modifyTime":1704533251,"name":"广州市 跑步","pitch":0,"rdType":0,"recalculateRecord":false,"recovery":false,"sets":0,"speedType":3,"speedValue":327,"speedValueDecimal":327.0,"sportType":100,"startLa":23.038999557495117,"startLo":113.38700103759766,"startTime":1704445073,"startTimeMs":"1704445073.76","startTimezone":32,"state":1,"step":5969,"subMode":1,"subSport":false,"taskStatus":0,"total":0,"totalAvgHr":0,"totalAvgSpeed":0,"totalDecline":1,"totalDeclineDouble":0.0,"totalElevation":0,"totalElevationDouble":0.0,"unit":2,"unitType":2,"uploadedImageData":0,"userId":447260452899012608,"uuid":"0027af48c8f00003fed90064168735e5","weatherLocationKey":"WS0DE3FVQQJF","weatherTime":1704442810},{"ascentDuration":0,"avgCadence":158,"avgHeartRate":149,"avgPace":297,"avgPower":236,"avgSpeed":0,"calorie":164405,"count":0,"countAvgHr":0,"countAvgSpeed":0,"createTimestamp":1704362042,"createTimezone":32,"deviceId":"COROS PACE 2 8735E5","deviceSportMode":0,"distance":2074.84,"distanceStatistics":0,"duration":617,"durationMs":"617.14","endTime":1704361793,"endTimeMs":"1704361793.74","endTimezone":32,"extraType":0,"fastKmV2":0,"filter":0,"fitCreateTime":"2024-01-04 17:54:19","fitUrl":"https://oss.coros.com/fit/447260452899012608/457511201952268288.fit","fitnessSwitch":0,"floors":0,"happenDate":20240104,"happenDay":20240104,"happenMonth":202401,"imageUrl":"https://map-oss-cn.coros.com/img/457511201950515200.jpg","imageUrlType":1,"isShowMs":1,"labelId":"457511201952268288","laps":0,"max2s":0,"maxSpeed":0,"mode":8,"modifyTime":1704533251,"name":"广州市 跑步","pitch":0,"rdType":0,"recalculateRecord":false,"recovery":false,"sets":0,"speedType":3,"speedValue":297,"speedValueDecimal":297.0,"sportType":100,"startLa":23.042999267578125,"startLo":113.38500213623047,"startTime":1704361103,"startTimeMs":"1704361103.64","startTimezone":32,"state":1,"step":1610,"subMode":1,"subSport":false,"taskStatus":0,"total":0,"totalAvgHr":0,"totalAvgSpeed":0,"totalDecline":2,"totalDeclineDouble":0.0,"totalElevation":0,"totalElevationDouble":0.0,"unit":2,"unitType":2,"uploadedImageData":0,"userId":447260452899012608,"uuid":"0027aec8a81c00010d920064168735e5","weatherLocationKey":"WS0DE3FVQQJF","weatherTime":1704360414},{"ascentDuration":0,"avgCadence":157,"avgHeartRate":152,"avgPace":325,"avgPower":224,"avgSpeed":0,"calorie":491638,"count":0,"countAvgHr":0,"countAvgSpeed":0,"createTimestamp":1704274338,"createTimezone":32,"deviceId":"COROS PACE 2 8735E5","deviceSportMode":0,"distance":6028.38,"distanceStatistics":0,"duration":1957,"durationMs":"1957.03","endTime":1704273790,"endTimeMs":"1704273790.84","endTimezone":32,"extraType":0,"fastKmV2":0,"filter":0,"fitCreateTime":"2024-01-03 17:32:37","fitUrl":"https://oss.coros.com/fit/447260452899012608/457487659089035264.fit","fitnessSwitch":0,"floors":0,"happenDate":20240103,"happenDay":20240103,"happenMonth":202401,"imageUrl":"https://map-oss-cn.coros.com/img/457487659089379328.jpg","imageUrlType":1,"isShowMs":1,"labelId":"457487659089035264","laps":0,"max2s":0,"maxSpeed":0,"mode":8,"modifyTime":1704274339,"name":"广州市 跑步","pitch":0,"rdType":0,"recalculateRecord":false,"recovery":false,"sets":0,"speedType":3,"speedValue":325,"speedValueDecimal":325.0,"sportType":100,"startLa":23.038999557495117,"startLo":113.38700103759766,"startTime":1704271287,"startTimeMs":"1704271287.47","startTimezone":32,"state":1,"step":5011,"subMode":1,"subSport":false,"taskStatus":0,"total":0,"totalAvgHr":0,"totalAvgSpeed":0,"totalDecline":12,"totalDeclineDouble":0.0,"totalElevation":7,"totalElevationDouble":0.0,"unit":2,"unitType":2,"uploadedImageData":0,"userId":447260452899012608,"uuid":"0027ae3f9bab0003d1e10064168735e5","weatherLocationKey":"WS0DE3FVQQJF","weatherTime":1704270138}],"message":"成功","result":"0000","tLogId":"39111098370106995384320"}